jupyter_a2a/__init__.py
jupyter_a2a/__version__.py
jupyter_a2a-0.0.1.dist-info/METADATA
jupyter_a2a-0.0.1.dist-info/WHEEL
jupyter_a2a-0.0.1.dist-info/entry_points.txt
jupyter_a2a-0.0.1.dist-info/licenses/LICENSE
jupyter_a2a-0.0.1.dist-info/RECORD
