Metadata-Version: 2.4
Name: jupyter_a2a
Version: 0.0.1
Project-URL: Home, https://github.com/datalayer/jupyter-a2a
Author-email: Datalayer <info@datalayer.io>
License: BSD 3-Clause License
License-File: LICENSE
Keywords: Jupyter
Classifier: Intended Audience :: Developers
Classifier: Intended Audience :: System Administrators
Classifier: License :: OSI Approved :: BSD License
Classifier: Programming Language :: Python
Classifier: Programming Language :: Python :: 3
Requires-Python: >=3.10
Requires-Dist: click
Requires-Dist: fastapi
Requires-Dist: jupyter-kernel-client>=0.7.3
Requires-Dist: jupyter-nbmodel-client>=0.13.5
Requires-Dist: jupyter-server-api
Requires-Dist: pydantic
Requires-Dist: uvicorn
Provides-Extra: lint
Requires-Dist: mdformat-gfm>=0.3.5; extra == 'lint'
Requires-Dist: mdformat>0.7; extra == 'lint'
Requires-Dist: ruff; extra == 'lint'
Provides-Extra: test
Requires-Dist: datalayer-pycrdt==0.12.17; extra == 'test'
Requires-Dist: ipykernel; extra == 'test'
Requires-Dist: jupyter-collaboration==4.0.2; extra == 'test'
Requires-Dist: jupyter-server<3,>=1.6; extra == 'test'
Requires-Dist: jupyterlab==4.4.1; extra == 'test'
Requires-Dist: pillow>=10.0.0; extra == 'test'
Requires-Dist: pytest-asyncio; extra == 'test'
Requires-Dist: pytest-timeout>=2.1.0; extra == 'test'
Requires-Dist: pytest>=7.0; extra == 'test'
Provides-Extra: typing
Requires-Dist: mypy>=0.990; extra == 'typing'
